semban/__init__.py
semban/semban.py
semban-0.1.0.dist-info/METADATA
semban-0.1.0.dist-info/WHEEL
semban-0.1.0.dist-info/top_level.txt
semban-0.1.0.dist-info/RECORD
