Metadata-Version: 2.1
Name: semban
Version: 0.1.0
Summary: Simple wrapper for g4f chat client
Home-page: UNKNOWN
Author: sidh2690
Author-email: you@example.com
License: UNKNOWN
Platform: UNKNOWN
Requires-Python: >=3.7
Requires-Dist: g4f (>=0.1.0)
